olt_devices_harvestor/__init__.py
olt_devices_harvestor/device_harvester.py
nokia_olt_device_harvester-0.0.3.dist-info/LICENSE.md
nokia_olt_device_harvester-0.0.3.dist-info/METADATA
nokia_olt_device_harvester-0.0.3.dist-info/WHEEL
nokia_olt_device_harvester-0.0.3.dist-info/top_level.txt
nokia_olt_device_harvester-0.0.3.dist-info/RECORD
