Metadata-Version: 2.1
Name: nokia-olt-device-harvester
Version: 0.0.3
Summary: Network Automation and Programmability Abstraction for Nokia OLT.     This package is intended to be used by applications that     need to feed the network 'Single Source Of Truth' with the     exact physical state of the network topology with 100% accuracy.
Home-page: https://github.com/djohnnes/
Author: David Johnnes
Author-email: david.johnnes@gmail.com
License: UNKNOWN
Keywords: nokia,olt,devices harvester
Platform: UNKNOWN
Classifier: Topic :: Utilities
Classifier: Programming Language :: Python :: 3
Classifier: Operating System :: OS Independent
Classifier: License :: OSI Approved :: BSD License
License-File: LICENSE.md
Requires-Dist: mac-vendor-lookup
Requires-Dist: paramiko
Requires-Dist: sshFRIEND
